odoo/addons/account_payment_repair/README.rst
odoo/addons/account_payment_repair/__init__.py
odoo/addons/account_payment_repair/__manifest__.py
odoo/addons/account_payment_repair/i18n/account_payment_repair.pot
odoo/addons/account_payment_repair/i18n/es.po
odoo/addons/account_payment_repair/i18n/fr.po
odoo/addons/account_payment_repair/models/__init__.py
odoo/addons/account_payment_repair/models/repair_order.py
odoo/addons/account_payment_repair/readme/CONFIGURE.rst
odoo/addons/account_payment_repair/readme/CONTRIBUTORS.rst
odoo/addons/account_payment_repair/readme/CREDITS.rst
odoo/addons/account_payment_repair/readme/DESCRIPTION.rst
odoo/addons/account_payment_repair/readme/USAGE.rst
odoo/addons/account_payment_repair/report/repair_report_templates.xml
odoo/addons/account_payment_repair/static/description/icon.png
odoo/addons/account_payment_repair/static/description/index.html
odoo/addons/account_payment_repair/tests/__init__.py
odoo/addons/account_payment_repair/tests/test_repair.py
odoo/addons/account_payment_repair/views/repair_order.xml
odoo12_addon_account_payment_repair-12.0.1.0.0.99.dev8.dist-info/METADATA
odoo12_addon_account_payment_repair-12.0.1.0.0.99.dev8.dist-info/WHEEL
odoo12_addon_account_payment_repair-12.0.1.0.0.99.dev8.dist-info/top_level.txt
odoo12_addon_account_payment_repair-12.0.1.0.0.99.dev8.dist-info/RECORD
